{"trial_id": "05", "hyperparameters": {"space": [{"class_name": "Int", "config": {"name": "units", "default": null, "conditions": [], "min_value": 32, "max_value": 512, "step": 32, "sampling": "linear"}}, {"class_name": "Choice", "config": {"name": "dense_activation", "default": "sigmoid", "conditions": [], "values": ["relu", "sigmoid"], "ordered": false}}, {"class_name": "Choice", "config": {"name": "learning_rate", "default": 0.01, "conditions": [], "values": [0.01, 0.001, 0.0001], "ordered": true}}], "values": {"units": 320, "dense_activation": "relu", "learning_rate": 0.0001}}, "metrics": {"metrics": {"loss": {"direction": "min", "observations": [{"value": [0.5103204399347305], "step": 1}]}, "precision": {"direction": "min", "observations": [{"value": [0.0978417694568634], "step": 1}]}, "recall": {"direction": "min", "observations": [{"value": [0.04484732821583748], "step": 1}]}, "auc": {"direction": "max", "observations": [{"value": [0.6913470923900604], "step": 1}]}, "binary_accuracy": {"direction": "max", "observations": [{"value": [0.9832006692886353], "step": 1}]}, "val_loss": {"direction": "min", "observations": [{"value": [0.3781561553478241], "step": 1}]}, "val_precision": {"direction": "min", "observations": [{"value": [0.027450980618596077], "step": 1}]}, "val_recall": {"direction": "min", "observations": [{"value": [0.027131782844662666], "step": 1}]}, "val_auc": {"direction": "min", "observations": [{"value": [0.690076619386673], "step": 1}]}, "val_binary_accuracy": {"direction": "max", "observations": [{"value": [0.9829469621181488], "step": 1}]}}}, "score": 0.6913470923900604, "best_step": 1, "status": "COMPLETED", "message": null}