{"trial_id": "02", "hyperparameters": {"space": [{"class_name": "Int", "config": {"name": "units", "default": null, "conditions": [], "min_value": 32, "max_value": 512, "step": 32, "sampling": "linear"}}, {"class_name": "Choice", "config": {"name": "dense_activation", "default": "sigmoid", "conditions": [], "values": ["relu", "sigmoid"], "ordered": false}}, {"class_name": "Choice", "config": {"name": "learning_rate", "default": 0.01, "conditions": [], "values": [0.01, 0.001, 0.0001], "ordered": true}}], "values": {"units": 512, "dense_activation": "sigmoid", "learning_rate": 0.001}}, "metrics": {"metrics": {"loss": {"direction": "min", "observations": [{"value": [0.06318644434213638], "step": 3}]}, "precision": {"direction": "min", "observations": [{"value": [0.16041667014360428], "step": 3}]}, "recall": {"direction": "min", "observations": [{"value": [0.00477099244017154], "step": 3}]}, "auc": {"direction": "max", "observations": [{"value": [0.7369371056556702], "step": 3}]}, "binary_accuracy": {"direction": "max", "observations": [{"value": [0.9879148900508881], "step": 3}]}, "val_loss": {"direction": "min", "observations": [{"value": [0.06513341888785362], "step": 3}]}, "val_precision": {"direction": "min", "observations": [{"value": [0.0923076942563057], "step": 3}]}, "val_recall": {"direction": "min", "observations": [{"value": [0.023255813866853714], "step": 3}]}, "val_auc": {"direction": "min", "observations": [{"value": [0.7225517928600311], "step": 3}]}, "val_binary_accuracy": {"direction": "max", "observations": [{"value": [0.9872159659862518], "step": 3}]}}}, "score": 0.7369371056556702, "best_step": 3, "status": "COMPLETED", "message": null}